{
  "companyId": "lu2rRu4YIxczwnjQpQ8pRpFUVlQ2",
  "timestamp": "2025-11-02T08:56:51.362Z",
  "expectedBalanceOldSystem": 280900,
  "currentBalance": 280900,
  "expectedBalanceFromData": 297900,
  "differences": {
    "currentVsOldSystem": 0,
    "adjustedVsOldSystem": 17000
  },
  "breakdown": {
    "sales": {
      "count": 125,
      "amount": 1458700
    },
    "expenses": {
      "count": 39,
      "amount": -209200
    },
    "manual": {
      "count": 24,
      "amount": -978600
    },
    "supplier": {
      "count": 0,
      "amount": 0
    },
    "other": {
      "count": 0,
      "amount": 0
    }
  },
  "missingFinanceEntries": {
    "sales": {
      "count": 3,
      "amount": 17000,
      "list": [
        {
          "docId": "1gsuGYWZDBMZIK1pIufx",
          "amount": 8000,
          "customer": "Divers",
          "date": "2025-11-01T13:17:28.575Z"
        },
        {
          "docId": "3YCiB73kwmuIW1jDs8WX",
          "amount": 5000,
          "customer": "Divers",
          "date": "2025-11-02T07:02:26.642Z"
        },
        {
          "docId": "HgMEjWmEoAUbpd7Tc7IP",
          "amount": 4000,
          "customer": "Divers",
          "date": "2025-11-01T13:07:08.042Z"
        }
      ]
    },
    "expenses": {
      "count": 0,
      "amount": 0,
      "list": []
    }
  },
  "orphanedFinanceEntries": {
    "sales": [],
    "expenses": []
  },
  "totals": {
    "salesFromSalesCollection": 1474700,
    "salesFromFinanceEntries": 1458700,
    "expensesFromExpensesCollection": -199200,
    "expensesFromFinanceEntries": -209200
  }
}